[
  {
    "ingredient": 3668,
    "name": "dried oregano",
    "count": 1
  },
  {
    "ingredient": 3936,
    "name": "head cauliflower cut into large florets",
    "count": 1
  },
  {
    "ingredient": 3845,
    "name": "great northern beans drained",
    "count": 1
  },
  {
    "ingredient": 3880,
    "name": "russet potatoes into",
    "count": 1
  },
  {
    "ingredient": 3839,
    "name": "crispy rice cereal",
    "count": 1
  },
  {
    "ingredient": 3915,
    "name": "mexican style hot sauce such valentina",
    "count": 1
  },
  {
    "ingredient": 3642,
    "name": "taco seasoning mix",
    "count": 1
  },
  {
    "ingredient": 3759,
    "name": "dijon mustard",
    "count": 1
  },
  {
    "ingredient": 3944,
    "name": "sweet italian sausage",
    "count": 1
  },
  {
    "ingredient": 3930,
    "name": "white pepper",
    "count": 1
  },
  {
    "ingredient": 3762,
    "name": "bottle hot pepper sauce",
    "count": 1
  },
  {
    "ingredient": 3928,
    "name": "montreal style steak seasoning",
    "count": 1
  },
  {
    "ingredient": 3637,
    "name": "buttermilk",
    "count": 1
  },
  {
    "ingredient": 3674,
    "name": "sweet potato cubed",
    "count": 1
  },
  {
    "ingredient": 3776,
    "name": "fresh mushrooms",
    "count": 1
  },
  {
    "ingredient": 3871,
    "name": "hot water",
    "count": 1
  },
  {
    "ingredient": 3751,
    "name": "roma plum tomatoes",
    "count": 1
  },
  {
    "ingredient": 3830,
    "name": "chicken breast cut into cubes",
    "count": 1
  },
  {
    "ingredient": 3811,
    "name": "low sodium chicken broth needed",
    "count": 1
  },
  {
    "ingredient": 3903,
    "name": "half half cream",
    "count": 1
  },
  {
    "ingredient": 3647,
    "name": "low fat sour cream",
    "count": 1
  },
  {
    "ingredient": 3653,
    "name": "mushrooms",
    "count": 1
  },
  {
    "ingredient": 3743,
    "name": "loaf processed cheese food such velveeta cubed",
    "count": 1
  },
  {
    "ingredient": 3739,
    "name": "cans condensed cream chicken soup",
    "count": 1
  },
  {
    "ingredient": 3648,
    "name": "avocado pitted",
    "count": 1
  },
  {
    "ingredient": 3908,
    "name": "egg noodles",
    "count": 1
  },
  {
    "ingredient": 3673,
    "name": "bell peppers seeded",
    "count": 1
  },
  {
    "ingredient": 3935,
    "name": "chicken breast cut into strips",
    "count": 1
  },
  {
    "ingredient": 3688,
    "name": "dry bread crumbs",
    "count": 1
  },
  {
    "ingredient": 3894,
    "name": "tomato juice",
    "count": 1
  },
  {
    "ingredient": 3719,
    "name": "chicken breast",
    "count": 1
  },
  {
    "ingredient": 3692,
    "name": "salt black pepper",
    "count": 1
  },
  {
    "ingredient": 3732,
    "name": "garlic powder",
    "count": 1
  },
  {
    "ingredient": 3797,
    "name": "chicken stock",
    "count": 1
  },
  {
    "ingredient": 3741,
    "name": "medium shrimp deveined",
    "count": 1
  },
  {
    "ingredient": 3754,
    "name": "egg yolks beaten",
    "count": 1
  },
  {
    "ingredient": 3937,
    "name": "butter more",
    "count": 1
  },
  {
    "ingredient": 3792,
    "name": "hot pepper sauce tabasco",
    "count": 1
  },
  {
    "ingredient": 3659,
    "name": "medium carrots cut into chunks",
    "count": 1
  },
  {
    "ingredient": 3742,
    "name": "tomatoes with green chile peppers such tel drained",
    "count": 1
  },
  {
    "ingredient": 3866,
    "name": "elbow macaroni",
    "count": 1
  },
  {
    "ingredient": 3786,
    "name": "green chile peppers seeded",
    "count": 1
  },
  {
    "ingredient": 3663,
    "name": "bulk italian sausage",
    "count": 1
  },
  {
    "ingredient": 3686,
    "name": "freshly black pepper",
    "count": 1
  },
  {
    "ingredient": 3713,
    "name": "carrots",
    "count": 1
  },
  {
    "ingredient": 3817,
    "name": "flour tortillas",
    "count": 1
  },
  {
    "ingredient": 3652,
    "name": "vegetable oil",
    "count": 1
  },
  {
    "ingredient": 3661,
    "name": "sprig fresh rosemary",
    "count": 1
  },
  {
    "ingredient": 3851,
    "name": "green bell peppers",
    "count": 1
  },
  {
    "ingredient": 3654,
    "name": "medium onion",
    "count": 1
  },
  {
    "ingredient": 3918,
    "name": "white rice",
    "count": 1
  },
  {
    "ingredient": 3934,
    "name": "hot sauce",
    "count": 1
  },
  {
    "ingredient": 3644,
    "name": "tomato",
    "count": 1
  },
  {
    "ingredient": 3717,
    "name": "lime juiced",
    "count": 1
  },
  {
    "ingredient": 3750,
    "name": "avocados pitted mashed",
    "count": 1
  },
  {
    "ingredient": 3747,
    "name": "jalapeno pepper",
    "count": 1
  },
  {
    "ingredient": 3771,
    "name": "wide egg noodles",
    "count": 1
  },
  {
    "ingredient": 3828,
    "name": "dash sesame oil",
    "count": 1
  },
  {
    "ingredient": 3678,
    "name": "fresh rosemary",
    "count": 1
  },
  {
    "ingredient": 3906,
    "name": "rubbed sage",
    "count": 1
  },
  {
    "ingredient": 3929,
    "name": "grated cheddar cheese",
    "count": 1
  },
  {
    "ingredient": 3777,
    "name": "crumbled feta cheese",
    "count": 1
  },
  {
    "ingredient": 3805,
    "name": "jalapeno peppers into rings",
    "count": 1
  },
  {
    "ingredient": 3795,
    "name": "chicken thighs",
    "count": 1
  },
  {
    "ingredient": 3914,
    "name": "thick pork chops",
    "count": 1
  },
  {
    "ingredient": 3714,
    "name": "stalk celery",
    "count": 1
  },
  {
    "ingredient": 3900,
    "name": "dash hot sauce",
    "count": 1
  },
  {
    "ingredient": 3718,
    "name": "fresh cilantro",
    "count": 1
  },
  {
    "ingredient": 3638,
    "name": "fresh blueberries rinsed drained patted dry",
    "count": 1
  },
  {
    "ingredient": 3933,
    "name": "fresh ginger root",
    "count": 1
  },
  {
    "ingredient": 3746,
    "name": "green onion",
    "count": 1
  },
  {
    "ingredient": 3691,
    "name": "beef stew meat",
    "count": 1
  },
  {
    "ingredient": 3773,
    "name": "tub sun dried tomato pesto",
    "count": 1
  },
  {
    "ingredient": 3916,
    "name": "brown sugar more",
    "count": 1
  },
  {
    "ingredient": 3814,
    "name": "grated parmigiano reggiano cheese",
    "count": 1
  },
  {
    "ingredient": 3910,
    "name": "butter margarine",
    "count": 1
  },
  {
    "ingredient": 3681,
    "name": "salt freshly black pepper",
    "count": 1
  },
  {
    "ingredient": 3782,
    "name": "large yellow onion",
    "count": 1
  },
  {
    "ingredient": 3685,
    "name": "kosher salt",
    "count": 1
  },
  {
    "ingredient": 3820,
    "name": "frozen green peas",
    "count": 1
  },
  {
    "ingredient": 3941,
    "name": "prepared marinara sauce",
    "count": 1
  },
  {
    "ingredient": 3921,
    "name": "pork loin chops pounded",
    "count": 1
  },
  {
    "ingredient": 3778,
    "name": "beef chuck",
    "count": 1
  },
  {
    "ingredient": 3822,
    "name": "unbaked pie crusts",
    "count": 1
  },
  {
    "ingredient": 3865,
    "name": "bacon",
    "count": 1
  },
  {
    "ingredient": 3924,
    "name": "mirin japanese sweet wine",
    "count": 1
  },
  {
    "ingredient": 3815,
    "name": "dried parsley",
    "count": 1
  },
  {
    "ingredient": 3893,
    "name": "cut green beans drained",
    "count": 1
  },
  {
    "ingredient": 3823,
    "name": "baking soda",
    "count": 1
  },
  {
    "ingredient": 3867,
    "name": "condensed cream mushroom soup",
    "count": 1
  },
  {
    "ingredient": 3749,
    "name": "cheddar cheese",
    "count": 1
  },
  {
    "ingredient": 3912,
    "name": "dry white wine",
    "count": 1
  },
  {
    "ingredient": 3756,
    "name": "vegetable oil for frying",
    "count": 1
  },
  {
    "ingredient": 3818,
    "name": "jar taco sauce",
    "count": 1
  },
  {
    "ingredient": 3920,
    "name": "lemon juice",
    "count": 1
  },
  {
    "ingredient": 3833,
    "name": "chile paste such thai kitchen",
    "count": 1
  },
  {
    "ingredient": 3670,
    "name": "black pepper",
    "count": 1
  },
  {
    "ingredient": 3699,
    "name": "tomato sauce",
    "count": 1
  },
  {
    "ingredient": 3709,
    "name": "bay leaf",
    "count": 1
  },
  {
    "ingredient": 3710,
    "name": "paprika",
    "count": 1
  },
  {
    "ingredient": 3729,
    "name": "soy sauce",
    "count": 1
  },
  {
    "ingredient": 3931,
    "name": "onions quartered",
    "count": 1
  },
  {
    "ingredient": 3876,
    "name": "vegetable broth",
    "count": 1
  },
  {
    "ingredient": 3666,
    "name": "low sodium chicken broth",
    "count": 1
  },
  {
    "ingredient": 3901,
    "name": "corn syrup",
    "count": 1
  },
  {
    "ingredient": 3635,
    "name": "all purpose flour",
    "count": 1
  },
  {
    "ingredient": 3669,
    "name": "pepper flakes more",
    "count": 1
  },
  {
    "ingredient": 3641,
    "name": "jalapeno peppers",
    "count": 1
  },
  {
    "ingredient": 3898,
    "name": "chili sauce",
    "count": 1
  },
  {
    "ingredient": 3911,
    "name": "prosciutto",
    "count": 1
  },
  {
    "ingredient": 3841,
    "name": "brown sugar",
    "count": 1
  },
  {
    "ingredient": 3728,
    "name": "honey",
    "count": 1
  },
  {
    "ingredient": 3701,
    "name": "bay leaves",
    "count": 1
  },
  {
    "ingredient": 3633,
    "name": "salt",
    "count": 1
  },
  {
    "ingredient": 3772,
    "name": "chicken breast cubed",
    "count": 1
  },
  {
    "ingredient": 3698,
    "name": "tip roast",
    "count": 1
  },
  {
    "ingredient": 3730,
    "name": "ketchup",
    "count": 1
  },
  {
    "ingredient": 3827,
    "name": "dry sherry",
    "count": 1
  },
  {
    "ingredient": 3793,
    "name": "dried basil",
    "count": 1
  },
  {
    "ingredient": 3922,
    "name": "marsala wine",
    "count": 1
  },
  {
    "ingredient": 3781,
    "name": "cans tomatoes with juice",
    "count": 1
  },
  {
    "ingredient": 3671,
    "name": "torn kale leaves bite size pieces",
    "count": 1
  },
  {
    "ingredient": 3831,
    "name": "distilled white vinegar",
    "count": 1
  },
  {
    "ingredient": 3949,
    "name": "lasagna noodles",
    "count": 1
  },
  {
    "ingredient": 3862,
    "name": "dry onion soup mix",
    "count": 1
  },
  {
    "ingredient": 3682,
    "name": "whole milk ricotta cheese",
    "count": 1
  },
  {
    "ingredient": 3704,
    "name": "seasoned salt",
    "count": 1
  },
  {
    "ingredient": 3779,
    "name": "cans chili beans drained",
    "count": 1
  },
  {
    "ingredient": 3939,
    "name": "salmon steaks",
    "count": 1
  },
  {
    "ingredient": 3738,
    "name": "milk",
    "count": 1
  },
  {
    "ingredient": 3675,
    "name": "yukon gold potatoes cubed",
    "count": 1
  },
  {
    "ingredient": 3808,
    "name": "unsweetened cocoa powder",
    "count": 1
  },
  {
    "ingredient": 3667,
    "name": "whole milk",
    "count": 1
  },
  {
    "ingredient": 3847,
    "name": "frozen corn",
    "count": 1
  },
  {
    "ingredient": 3664,
    "name": "half half",
    "count": 1
  },
  {
    "ingredient": 3840,
    "name": "chicken breast cut half",
    "count": 1
  },
  {
    "ingredient": 3800,
    "name": "sharp cheddar cheese",
    "count": 1
  },
  {
    "ingredient": 3640,
    "name": "onion",
    "count": 1
  },
  {
    "ingredient": 3806,
    "name": "onion cut into chunks",
    "count": 1
  },
  {
    "ingredient": 3897,
    "name": "pork baby back ribs",
    "count": 1
  },
  {
    "ingredient": 3763,
    "name": "butter cubed",
    "count": 1
  },
  {
    "ingredient": 3784,
    "name": "green bell pepper seeded",
    "count": 1
  },
  {
    "ingredient": 3854,
    "name": "crabmeat",
    "count": 1
  },
  {
    "ingredient": 3802,
    "name": "mexican crema sour cream",
    "count": 1
  },
  {
    "ingredient": 3945,
    "name": "cans tomato paste",
    "count": 1
  },
  {
    "ingredient": 3748,
    "name": "black beans rinsed drained",
    "count": 1
  },
  {
    "ingredient": 3766,
    "name": "carrot",
    "count": 1
  },
  {
    "ingredient": 3848,
    "name": "white vinegar",
    "count": 1
  },
  {
    "ingredient": 3803,
    "name": "plum tomatoes cut into",
    "count": 1
  },
  {
    "ingredient": 3745,
    "name": "sour cream",
    "count": 1
  },
  {
    "ingredient": 3694,
    "name": "potatoes",
    "count": 1
  },
  {
    "ingredient": 3913,
    "name": "seasoning salt",
    "count": 1
  },
  {
    "ingredient": 3812,
    "name": "orecchiette pasta more",
    "count": 1
  },
  {
    "ingredient": 3927,
    "name": "frozen bite size potato nuggets such tater tots",
    "count": 1
  },
  {
    "ingredient": 3895,
    "name": "chicken wings",
    "count": 1
  },
  {
    "ingredient": 3896,
    "name": "hot pepper sauce such frank redhot",
    "count": 1
  },
  {
    "ingredient": 3662,
    "name": "sprigs fresh thyme",
    "count": 1
  },
  {
    "ingredient": 3783,
    "name": "stalks celery",
    "count": 1
  },
  {
    "ingredient": 3765,
    "name": "blue cheese salad dressing",
    "count": 1
  },
  {
    "ingredient": 3715,
    "name": "jar salsa",
    "count": 1
  },
  {
    "ingredient": 3768,
    "name": "fresh thyme leaves",
    "count": 1
  },
  {
    "ingredient": 3660,
    "name": "stalks celery cut into chunks",
    "count": 1
  },
  {
    "ingredient": 3819,
    "name": "potatoes halved",
    "count": 1
  },
  {
    "ingredient": 3905,
    "name": "seasoned bread crumbs",
    "count": 1
  },
  {
    "ingredient": 3834,
    "name": "toasted sesame seeds",
    "count": 1
  },
  {
    "ingredient": 3861,
    "name": "mild sage flavored breakfast sausage",
    "count": 1
  },
  {
    "ingredient": 3695,
    "name": "tomatoes",
    "count": 1
  },
  {
    "ingredient": 3631,
    "name": "unsalted butter",
    "count": 1
  },
  {
    "ingredient": 3789,
    "name": "beer",
    "count": 1
  },
  {
    "ingredient": 3923,
    "name": "low sodium soy sauce",
    "count": 1
  },
  {
    "ingredient": 3829,
    "name": "canola oil",
    "count": 1
  },
  {
    "ingredient": 3684,
    "name": "egg beaten",
    "count": 1
  },
  {
    "ingredient": 3780,
    "name": "chili beans spicy sauce",
    "count": 1
  },
  {
    "ingredient": 3676,
    "name": "onion quartered",
    "count": 1
  },
  {
    "ingredient": 3804,
    "name": "peppers cut into chunks",
    "count": 1
  },
  {
    "ingredient": 3872,
    "name": "walnuts",
    "count": 1
  },
  {
    "ingredient": 3775,
    "name": "bunch spinach rinsed",
    "count": 1
  },
  {
    "ingredient": 3757,
    "name": "whole chicken cut into pieces",
    "count": 1
  },
  {
    "ingredient": 3769,
    "name": "chicken fat",
    "count": 1
  },
  {
    "ingredient": 3855,
    "name": "fresh parsley",
    "count": 1
  },
  {
    "ingredient": 3736,
    "name": "envelope dry onion soup mix",
    "count": 1
  },
  {
    "ingredient": 3656,
    "name": "butter",
    "count": 1
  },
  {
    "ingredient": 3889,
    "name": "pepperoni",
    "count": 1
  },
  {
    "ingredient": 3680,
    "name": "balsamic vinegar",
    "count": 1
  },
  {
    "ingredient": 3735,
    "name": "lean beef",
    "count": 1
  },
  {
    "ingredient": 3658,
    "name": "chicken broth",
    "count": 1
  },
  {
    "ingredient": 3703,
    "name": "jar meatless spaghetti sauce",
    "count": 1
  },
  {
    "ingredient": 3879,
    "name": "buttermilk biscuits",
    "count": 1
  },
  {
    "ingredient": 3696,
    "name": "jar sofrito",
    "count": 1
  },
  {
    "ingredient": 3813,
    "name": "roughly arugula",
    "count": 1
  },
  {
    "ingredient": 3807,
    "name": "vanilla extract",
    "count": 1
  },
  {
    "ingredient": 3689,
    "name": "jar marinara sauce",
    "count": 1
  },
  {
    "ingredient": 3892,
    "name": "large head cabbage",
    "count": 1
  },
  {
    "ingredient": 3767,
    "name": "celery",
    "count": 1
  },
  {
    "ingredient": 3849,
    "name": "dried cilantro",
    "count": 1
  },
  {
    "ingredient": 3711,
    "name": "worcestershire sauce",
    "count": 1
  },
  {
    "ingredient": 3785,
    "name": "bell pepper seeded",
    "count": 1
  },
  {
    "ingredient": 3760,
    "name": "fresh tarragon",
    "count": 1
  },
  {
    "ingredient": 3645,
    "name": "reduced fat cheddar cheese",
    "count": 1
  },
  {
    "ingredient": 3904,
    "name": "brandy based orange liqueur such grand marnier",
    "count": 1
  },
  {
    "ingredient": 3919,
    "name": "extra lean beef",
    "count": 1
  },
  {
    "ingredient": 3950,
    "name": "ricotta cheese",
    "count": 1
  },
  {
    "ingredient": 3649,
    "name": "beef pot roast",
    "count": 1
  },
  {
    "ingredient": 3655,
    "name": "garlic",
    "count": 1
  },
  {
    "ingredient": 3770,
    "name": "roasted chicken broth see footnote for recipe link",
    "count": 1
  },
  {
    "ingredient": 3724,
    "name": "pepper flakes",
    "count": 1
  },
  {
    "ingredient": 3634,
    "name": "eggs",
    "count": 1
  },
  {
    "ingredient": 3874,
    "name": "cider vinegar",
    "count": 1
  },
  {
    "ingredient": 3836,
    "name": "strips bacon",
    "count": 1
  },
  {
    "ingredient": 3712,
    "name": "beef broth",
    "count": 1
  },
  {
    "ingredient": 3869,
    "name": "cheddar cheese cubed",
    "count": 1
  },
  {
    "ingredient": 3946,
    "name": "cans tomato sauce",
    "count": 1
  },
  {
    "ingredient": 3875,
    "name": "ginger",
    "count": 1
  },
  {
    "ingredient": 3948,
    "name": "italian seasoning",
    "count": 1
  },
  {
    "ingredient": 3890,
    "name": "onions",
    "count": 1
  },
  {
    "ingredient": 3940,
    "name": "bourbon whiskey",
    "count": 1
  },
  {
    "ingredient": 3632,
    "name": "white sugar",
    "count": 1
  },
  {
    "ingredient": 3809,
    "name": "semisweet chocolate chips",
    "count": 1
  },
  {
    "ingredient": 3700,
    "name": "onion cut into strips",
    "count": 1
  },
  {
    "ingredient": 3677,
    "name": "fresh thyme",
    "count": 1
  },
  {
    "ingredient": 3891,
    "name": "cans whole tomatoes with liquid",
    "count": 1
  },
  {
    "ingredient": 3856,
    "name": "mayonnaise",
    "count": 1
  },
  {
    "ingredient": 3657,
    "name": "tomato paste",
    "count": 1
  },
  {
    "ingredient": 3852,
    "name": "bell pepper",
    "count": 1
  },
  {
    "ingredient": 3672,
    "name": "small butternut squash cubed",
    "count": 1
  },
  {
    "ingredient": 3752,
    "name": "garlic salt",
    "count": 1
  },
  {
    "ingredient": 3690,
    "name": "water",
    "count": 1
  },
  {
    "ingredient": 3860,
    "name": "dried thyme",
    "count": 1
  },
  {
    "ingredient": 3926,
    "name": "cooking spray",
    "count": 1
  },
  {
    "ingredient": 3744,
    "name": "large chicken breast",
    "count": 1
  },
  {
    "ingredient": 3882,
    "name": "shortening",
    "count": 1
  },
  {
    "ingredient": 3938,
    "name": "dark brown sugar",
    "count": 1
  },
  {
    "ingredient": 3705,
    "name": "grated parmesan cheese",
    "count": 1
  },
  {
    "ingredient": 3737,
    "name": "italian seasoned bread crumbs",
    "count": 1
  },
  {
    "ingredient": 3942,
    "name": "fresh basil",
    "count": 1
  },
  {
    "ingredient": 3665,
    "name": "cubed potatoes",
    "count": 1
  },
  {
    "ingredient": 3881,
    "name": "onion into rings",
    "count": 1
  },
  {
    "ingredient": 3832,
    "name": "sesame oil",
    "count": 1
  },
  {
    "ingredient": 3794,
    "name": "bag corn chips such fritos",
    "count": 1
  },
  {
    "ingredient": 3651,
    "name": "all purpose flour needed",
    "count": 1
  },
  {
    "ingredient": 3707,
    "name": "mozzarella cheese",
    "count": 1
  },
  {
    "ingredient": 3883,
    "name": "very ripe bananas mashed",
    "count": 1
  },
  {
    "ingredient": 3788,
    "name": "cubes beef bouillon",
    "count": 1
  },
  {
    "ingredient": 3821,
    "name": "celery seed",
    "count": 1
  },
  {
    "ingredient": 3693,
    "name": "spanish onion",
    "count": 1
  },
  {
    "ingredient": 3810,
    "name": "spicy italian sausages casings removed",
    "count": 1
  },
  {
    "ingredient": 3835,
    "name": "lemon pepper seasoning",
    "count": 1
  },
  {
    "ingredient": 3864,
    "name": "rolled oats more if desired",
    "count": 1
  },
  {
    "ingredient": 3943,
    "name": "garlic croutons",
    "count": 1
  },
  {
    "ingredient": 3734,
    "name": "sesame seeds",
    "count": 1
  },
  {
    "ingredient": 3884,
    "name": "semi sweet chocolate chips",
    "count": 1
  },
  {
    "ingredient": 3740,
    "name": "packet dry au jus mix",
    "count": 1
  },
  {
    "ingredient": 3824,
    "name": "packed brown sugar",
    "count": 1
  },
  {
    "ingredient": 3909,
    "name": "medium head green cabbage",
    "count": 1
  },
  {
    "ingredient": 3816,
    "name": "green bell pepper",
    "count": 1
  },
  {
    "ingredient": 3843,
    "name": "chicken breasts cut into chunks",
    "count": 1
  },
  {
    "ingredient": 3725,
    "name": "swiss chard",
    "count": 1
  },
  {
    "ingredient": 3844,
    "name": "black beans drained",
    "count": 1
  },
  {
    "ingredient": 3858,
    "name": "dash hot pepper sauce",
    "count": 1
  },
  {
    "ingredient": 3888,
    "name": "jars spaghetti sauce",
    "count": 1
  },
  {
    "ingredient": 3643,
    "name": "lettuce",
    "count": 1
  },
  {
    "ingredient": 3755,
    "name": "beer water",
    "count": 1
  },
  {
    "ingredient": 3842,
    "name": "wine",
    "count": 1
  },
  {
    "ingredient": 3716,
    "name": "dry taco seasoning mix",
    "count": 1
  },
  {
    "ingredient": 3863,
    "name": "barbeque sauce",
    "count": 1
  },
  {
    "ingredient": 3683,
    "name": "packed italian parsley",
    "count": 1
  },
  {
    "ingredient": 3723,
    "name": "chicken broth more needed",
    "count": 1
  },
  {
    "ingredient": 3873,
    "name": "cold water",
    "count": 1
  },
  {
    "ingredient": 3791,
    "name": "cumin",
    "count": 1
  },
  {
    "ingredient": 3697,
    "name": "pitted halved green olives",
    "count": 1
  },
  {
    "ingredient": 3727,
    "name": "grated parmigiano reggiano cheese plus additional for serving",
    "count": 1
  },
  {
    "ingredient": 3885,
    "name": "rigatoni pasta",
    "count": 1
  },
  {
    "ingredient": 3846,
    "name": "cans tomatoes with green chile peppers",
    "count": 1
  },
  {
    "ingredient": 3868,
    "name": "cans tuna drained",
    "count": 1
  },
  {
    "ingredient": 3722,
    "name": "dry elbow macaroni",
    "count": 1
  },
  {
    "ingredient": 3726,
    "name": "cannellini white kidney beans drained",
    "count": 1
  },
  {
    "ingredient": 3902,
    "name": "thick french bread",
    "count": 1
  },
  {
    "ingredient": 3646,
    "name": "salsa",
    "count": 1
  },
  {
    "ingredient": 3799,
    "name": "matchstick cut carrots",
    "count": 1
  },
  {
    "ingredient": 3774,
    "name": "whole wheat pita breads",
    "count": 1
  },
  {
    "ingredient": 3837,
    "name": "colby monterey jack cheese",
    "count": 1
  },
  {
    "ingredient": 3853,
    "name": "yellow bell pepper",
    "count": 1
  },
  {
    "ingredient": 3887,
    "name": "mushrooms drained",
    "count": 1
  },
  {
    "ingredient": 3721,
    "name": "yellow onion",
    "count": 1
  },
  {
    "ingredient": 3796,
    "name": "flour",
    "count": 1
  },
  {
    "ingredient": 3925,
    "name": "grated fresh ginger",
    "count": 1
  },
  {
    "ingredient": 3733,
    "name": "cornstarch",
    "count": 1
  },
  {
    "ingredient": 3758,
    "name": "heavy cream",
    "count": 1
  },
  {
    "ingredient": 3702,
    "name": "spaghetti",
    "count": 1
  },
  {
    "ingredient": 3790,
    "name": "chili powder",
    "count": 1
  },
  {
    "ingredient": 3932,
    "name": "whole chickens",
    "count": 1
  },
  {
    "ingredient": 3650,
    "name": "salt pepper",
    "count": 1
  },
  {
    "ingredient": 3708,
    "name": "beef stew meat cut into cubes",
    "count": 1
  },
  {
    "ingredient": 3761,
    "name": "chicken drumsticks",
    "count": 1
  },
  {
    "ingredient": 3731,
    "name": "dried onion",
    "count": 1
  },
  {
    "ingredient": 3877,
    "name": "condensed cream chicken soup",
    "count": 1
  },
  {
    "ingredient": 3886,
    "name": "italian sausage",
    "count": 1
  },
  {
    "ingredient": 3917,
    "name": "leaves cabbage",
    "count": 1
  },
  {
    "ingredient": 3870,
    "name": "seasoned croutons",
    "count": 1
  },
  {
    "ingredient": 3753,
    "name": "poultry seasoning",
    "count": 1
  },
  {
    "ingredient": 3857,
    "name": "dry mustard",
    "count": 1
  },
  {
    "ingredient": 3825,
    "name": "egg",
    "count": 1
  },
  {
    "ingredient": 3838,
    "name": "dried basil leaves",
    "count": 1
  },
  {
    "ingredient": 3679,
    "name": "olive oil",
    "count": 1
  },
  {
    "ingredient": 3764,
    "name": "onion powder",
    "count": 1
  },
  {
    "ingredient": 3801,
    "name": "whole chicken",
    "count": 1
  },
  {
    "ingredient": 3859,
    "name": "prime rib roast",
    "count": 1
  },
  {
    "ingredient": 3878,
    "name": "sweet corn drained",
    "count": 1
  },
  {
    "ingredient": 3850,
    "name": "dash salt",
    "count": 1
  },
  {
    "ingredient": 3639,
    "name": "beef",
    "count": 1
  },
  {
    "ingredient": 3826,
    "name": "egg yolk",
    "count": 1
  },
  {
    "ingredient": 3907,
    "name": "mustard",
    "count": 1
  },
  {
    "ingredient": 3687,
    "name": "cayenne pepper",
    "count": 1
  },
  {
    "ingredient": 3899,
    "name": "vinegar",
    "count": 1
  },
  {
    "ingredient": 3787,
    "name": "bacon bits",
    "count": 1
  },
  {
    "ingredient": 3798,
    "name": "coarsely broccoli florets",
    "count": 1
  },
  {
    "ingredient": 3947,
    "name": "fennel seeds",
    "count": 1
  },
  {
    "ingredient": 3636,
    "name": "baking powder",
    "count": 1
  },
  {
    "ingredient": 3720,
    "name": "sweet bulk italian sausage",
    "count": 1
  },
  {
    "ingredient": 3706,
    "name": "small curd cottage cheese",
    "count": 1
  }
]
